neuro_auth_client/__init__.py
neuro_auth_client/api.py
neuro_auth_client/bearer_auth.py
neuro_auth_client/client.py
neuro_auth_client/py.typed
neuro_auth_client/security.py
neuro_auth_client-25.8.2.dist-info/licenses/LICENSE
neuro_auth_client-25.8.2.dist-info/METADATA
neuro_auth_client-25.8.2.dist-info/WHEEL
neuro_auth_client-25.8.2.dist-info/top_level.txt
neuro_auth_client-25.8.2.dist-info/RECORD
