Metadata-Version: 2.4
Name: neuro-auth-client
Version: 25.8.2
Summary: Internal client for Neu.ro auth service
Home-page: https://github.com/neuro-inc/neuro-auth-client
License: Apache 2
Classifier: License :: OSI Approved :: Apache Software License
Classifier: Programming Language :: Python :: 3
Requires-Python: >=3.9
License-File: LICENSE
Requires-Dist: aiohttp>=3.8
Requires-Dist: aiohttp-security>=0.4.0
Requires-Dist: python-jose>=3.0.1
Dynamic: license-file
